[
    {
        "id": "2000",
        "slug": "skincare",
        "sort": 10,
        "visibleIn": [
            "site",
            "panel"
        ],
        "labels": {
            "tr": "Cilt Bakımı",
            "en": "Skincare",
            "de": "Hautpflege",
            "fr": "Soin du visage",
            "ru": "Уход за кожей"
        },
        "roleRequired": "editor",
        "routes": {
            "site": "/{lang}/shop/skincare",
            "admin": "/admin/catalog/skincare"
        },
        "featureFlags": {
            "EU": true
        },
        "children": [
            {
                "id": "2100",
                "slug": "sothys",
                "sort": 10,
                "visibleIn": [
                    "site",
                    "panel"
                ],
                "labels": {
                    "tr": "Sothys Paris",
                    "en": "Sothys Paris",
                    "de": "Sothys Paris",
                    "fr": "Sothys Paris",
                    "ru": "Sothys Paris"
                },
                "roleRequired": "editor",
                "routes": {
                    "site": "/{lang}/shop/skincare/sothys",
                    "admin": "/admin/brands/sothys"
                },
                "children": [
                    {
                        "id": "2110",
                        "slug": "hydra-ha4",
                        "sort": 10,
                        "visibleIn": [
                            "site",
                            "panel"
                        ],
                        "labels": {
                            "tr": "Hydra (Hyaluronic Acid4)",
                            "en": "Hydra (Hyaluronic Acid4)",
                            "de": "Hydra (Hyaluronic Acid4)",
                            "fr": "Hydra (Acide Hyaluronique4)",
                            "ru": "Hydra (Гиалуроновая кислота 4)"
                        },
                        "roleRequired": "editor",
                        "routes": {
                            "site": "/{lang}/shop/skincare/sothys/hydra-ha4",
                            "admin": "/admin/collections/hydra-ha4"
                        }
                    },
                    {
                        "id": "2120",
                        "slug": "sensitive-spa-water",
                        "sort": 20,
                        "visibleIn": [
                            "site",
                            "panel"
                        ],
                        "labels": {
                            "tr": "Hassas Cilt (Spa™ Thermal Water)",
                            "en": "Sensitive (Spa™ Thermal Water)",
                            "de": "Sensible Haut (Spa™ Thermal Water)",
                            "fr": "Peaux sensibles (Eau thermale Spa™)",
                            "ru": "Чувствительная кожа (Spa™)"
                        },
                        "roleRequired": "editor",
                        "routes": {
                            "site": "/{lang}/shop/skincare/sothys/sensitive-spa-water",
                            "admin": "/admin/collections/sensitive-spa-water"
                        }
                    }
                ]
            }
        ]
    }
]